llama_index/tools/scrapegraph/__init__.py
llama_index/tools/scrapegraph/base.py
llama_index_tools_scrapegraphai-0.2.2.dist-info/METADATA
llama_index_tools_scrapegraphai-0.2.2.dist-info/WHEEL
llama_index_tools_scrapegraphai-0.2.2.dist-info/licenses/LICENSE
llama_index_tools_scrapegraphai-0.2.2.dist-info/RECORD
