Metadata-Version: 2.4
Name: llama-index-tools-scrapegraphai
Version: 0.2.2
Summary: llama-index tools integrating ScrapegraphAI
Author-email: Marco Vinciguerra <mvincig11@gmail.com>
Maintainer: Vincigit00
License-Expression: MIT
License-File: LICENSE
Keywords: scraping
Requires-Python: <4.0,>=3.10
Requires-Dist: llama-index-core<0.15,>=0.13.0
Requires-Dist: scrapegraph-py<2,>=1.6.0
